fahadservermodule/__init__.py
fahadservermodule/server.py
fahadawsomeserver-0.1.1.dist-info/METADATA
fahadawsomeserver-0.1.1.dist-info/WHEEL
fahadawsomeserver-0.1.1.dist-info/entry_points.txt
fahadawsomeserver-0.1.1.dist-info/top_level.txt
fahadawsomeserver-0.1.1.dist-info/RECORD
