Metadata-Version: 2.4
Name: fahadAwsomeServer
Version: 0.1.1
Summary: A custom Model Context Protocol server developed in Python.
Author: Fahad Khan
Author-email: k.fahad1@tcs.com
Classifier: Programming Language :: Python :: 3
Classifier: License :: OSI Approved :: MIT License
Classifier: Operating System :: OS Independent
Requires-Python: >=3.10
Requires-Dist: mcp
Dynamic: author
Dynamic: author-email
Dynamic: classifier
Dynamic: description-content-type
Dynamic: requires-dist
Dynamic: requires-python
Dynamic: summary
